LICENSE
MANIFEST.in
README.md
setup.py
emeraldtriangles/__init__.py
emeraldtriangles/boundary.py
emeraldtriangles/cleanup.py
emeraldtriangles/distance.py
emeraldtriangles/interpolation.py
emeraldtriangles/plotting.py
emeraldtriangles/plotting_bokeh.py
emeraldtriangles/points_in_mesh.py
emeraldtriangles/projection.py
emeraldtriangles/raster.py
emeraldtriangles/refine_mesh.py
emeraldtriangles/sampling.py
emeraldtriangles.egg-info/PKG-INFO
emeraldtriangles.egg-info/SOURCES.txt
emeraldtriangles.egg-info/dependency_links.txt
emeraldtriangles.egg-info/requires.txt
emeraldtriangles.egg-info/top_level.txt
emeraldtriangles/io/__init__.py
emeraldtriangles/io/_landxml.pyx
emeraldtriangles/io/landxml.py
emeraldtriangles/io/libxml.pxd
emeraldtriangles/io/sql.py
emeraldtriangles/io/vtk/__init__.py
emeraldtriangles/io/vtk/surface.py
emeraldtriangles/io/vtk/volume.py