Metadata-Version: 2.1
Name: emeraldtriangles
Version: 0.1.2
Summary: Triangle mesh transforms
Home-page: https://github.com/EMeraldGeo/EmeraldTriangles
Author: Egil Moeller, Craig W. Christensen, et al.
Author-email: em@emrld.no
License-File: LICENSE
Requires-Dist: numpy==1.24.4
Requires-Dist: pandas
Requires-Dist: scipy
Requires-Dist: triangle
Requires-Dist: pandasio
Requires-Dist: lxml
Requires-Dist: matplotlib
Requires-Dist: shapely
Requires-Dist: geoalchemy2
Requires-Dist: pyproj
Requires-Dist: pyvista
Requires-Dist: scikit-gstat
Requires-Dist: bokeh
Requires-Dist: rasterio
